episode_monitor/__init__.py
episode_monitor/main.py
episode_monitor-1.2.0.dist-info/WHEEL
episode_monitor-1.2.0.dist-info/entry_points.txt
episode_monitor-1.2.0.dist-info/METADATA
episode_monitor-1.2.0.dist-info/RECORD
