Metadata-Version: 2.3
Name: episode-monitor
Version: 1.2.0
Summary: Monitor wikipedia pages of tv shows and send a notification when new episodes are detected
Requires-Dist: dbus-python>=1.4.0
Requires-Dist: notify2>=0.3.1
Requires-Dist: pyyaml>=6.0.2
Requires-Dist: requests>=2.32.5
Requires-Python: >=3.12
